<?xml version="1.0" encoding="UTF-8"?><record_update table="sn_cmp_rb_op_param">
    <sn_cmp_rb_op_param action="INSERT_OR_UPDATE">
        <interface display_value="Network Service Container Interface">7579b35e0be622009e620bcb15673a28</interface>
        <name>ResourceGroup</name>
        <operation display_value="CreateSubnet">fcba49a00bc13200668daac125673ada</operation>
        <order>1000</order>
        <sys_class_name>sn_cmp_rb_op_param</sys_class_name>
        <sys_created_by>admin</sys_created_by>
        <sys_created_on>2017-02-17 12:32:41</sys_created_on>
        <sys_id>d5db8db40b0132003969a387b6673a98</sys_id>
        <sys_mod_count>1</sys_mod_count>
        <sys_name>ResourceGroup</sys_name>
        <sys_package display_value="Cloud Management Platform" source="sn_cmp">80d50579eb203200979aa5115206fedd</sys_package>
        <sys_policy/>
        <sys_scope display_value="Cloud Management Platform">80d50579eb203200979aa5115206fedd</sys_scope>
        <sys_update_name>sn_cmp_rb_op_param_d5db8db40b0132003969a387b6673a98</sys_update_name>
        <sys_updated_by>admin</sys_updated_by>
        <sys_updated_on>2017-02-17 12:34:17</sys_updated_on>
        <type>1</type>
    </sn_cmp_rb_op_param>
</record_update>
