<?xml version="1.0" encoding="UTF-8"?><record_update table="sn_cmp_grid_definition">
    <sn_cmp_grid_definition action="INSERT_OR_UPDATE">
        <add_remove_rows/>
        <description>Grid to populate the override attributes for a given Application Profile</description>
        <name>Configuration Override</name>
        <sys_class_name>sn_cmp_grid_definition</sys_class_name>
        <sys_created_by>admin</sys_created_by>
        <sys_created_on>2017-08-23 20:32:59</sys_created_on>
        <sys_id>c20b758d0b3003003246ad4363673a16</sys_id>
        <sys_mod_count>0</sys_mod_count>
        <sys_name>Application Profile Override</sys_name>
        <sys_package display_value="Cloud Management Platform" source="sn_cmp">80d50579eb203200979aa5115206fedd</sys_package>
        <sys_policy/>
        <sys_scope display_value="Cloud Management Platform">80d50579eb203200979aa5115206fedd</sys_scope>
        <sys_update_name>sn_cmp_grid_definition_c20b758d0b3003003246ad4363673a16</sys_update_name>
        <sys_updated_by>admin</sys_updated_by>
        <sys_updated_on>2017-08-23 20:32:59</sys_updated_on>
    </sn_cmp_grid_definition>
</record_update>
